Metadata-Version: 1.1
Name: invalidroutesreporter
Version: 0.1.0
Summary: An ExaBGP process to elaborate and report/log invalid routes received by route servers.
Home-page: https://github.com/pierky/invalidroutesreporter
Author: Pier Carlo Chiodi
Author-email: pierky@pierky.com
License: GPLv3
Download-URL: https://github.com/pierky/invalidroutesreporter
Keywords: BGP,Route server,BIRD,IP Routing
Platform: UNKNOWN
Classifier: Development Status :: 4 - Beta
Classifier: Environment :: Console
Classifier: Intended Audience :: Information Technology
Classifier: Intended Audience :: System Administrators
Classifier: Intended Audience :: Telecommunications Industry
Classifier: License :: OSI Approved :: GNU General Public License v3 (GPLv3)
Classifier: Operating System :: POSIX
Classifier: Operating System :: Unix
Classifier: Programming Language :: Python
Classifier: Programming Language :: Python :: 2.7
Classifier: Topic :: Internet :: WWW/HTTP
Classifier: Topic :: System :: Networking
